{
  "nodes": [
    {"id": 0, "x": 0.0000, "y": 0.0000, "z": 0.0000, "val": 0.0000, "type": "register"},
    {"id": 1, "x": 0.0622, "y": 0.6904, "z": 0.6931, "val": 0.6931, "type": "register"},
    {"id": 2, "x": -1.1213, "y": 1.1545, "z": 1.6094, "val": 1.6094, "type": "register"},
    {"id": 3, "x": 0.0000, "y": 0.0000, "z": 0.0000, "val": 0.0000, "type": "register"},
    {"id": 4, "x": 0.0000, "y": 0.0000, "z": 0.0000, "val": 0.0000, "type": "register"},
    {"id": 5, "x": 0.0000, "y": 0.0000, "z": 0.0000, "val": 0.0000, "type": "register"},
    {"id": 6, "x": 0.0000, "y": 0.0000, "z": 0.0000, "val": 0.0000, "type": "register"},
    {"id": 7, "x": 0.0000, "y": 0.0000, "z": 0.0000, "val": 0.0000, "type": "register"},
    {"id": 8, "x": 0.0000, "y": 0.0000, "z": 0.0000, "val": 0.0000, "type": "register"},
    {"id": 9, "x": 0.0000, "y": 0.0000, "z": 0.0000, "val": 0.0000, "type": "register"},
    {"id": 10, "x": 0.0000, "y": 0.0000, "z": 0.0000, "val": 0.0000, "type": "register"},
    {"id": 11, "x": 0.0000, "y": 0.0000, "z": 0.0000, "val": 0.0000, "type": "register"},
    {"id": 12, "x": 0.0000, "y": 0.0000, "z": 0.0000, "val": 0.0000, "type": "register"},
    {"id": 13, "x": 0.0000, "y": 0.0000, "z": 0.0000, "val": 0.0000, "type": "register"},
    {"id": 14, "x": 0.0000, "y": 0.0000, "z": 0.0000, "val": 0.0000, "type": "register"},
    {"id": 15, "x": 0.0000, "y": 0.0000, "z": 0.0000, "val": 0.0000, "type": "register"}
  ],
  "links": [
    {"source": 0, "target": 1},
    {"source": 0, "target": 2}
  ]
}
